dictionaryio.py
tests/__init__.py
tests/test.py
dictionaryio-0.0.2.dist-info/LICENSE
dictionaryio-0.0.2.dist-info/METADATA
dictionaryio-0.0.2.dist-info/WHEEL
dictionaryio-0.0.2.dist-info/top_level.txt
dictionaryio-0.0.2.dist-info/RECORD
