Metadata-Version: 2.1
Name: dictionaryio
Version: 0.0.2
Summary: An English dictionary wrapper with voice-pronunciation enabled
Home-page: https://github.com/luckyadogun/dictionaryIO
Author: Lucky Adogun
Author-email: meetluckyadogun@gmail.com
License: UNKNOWN
Platform: UNKNOWN
Classifier: Programming Language :: Python :: 3
Classifier: License :: OSI Approved :: MIT License
Classifier: Operating System :: OS Independent
Requires-Python: >=3.6
